[
  {
    "mandi_id": "MKT-KIB",
    "name": "Kibuye",
    "district": "Kisumu",
    "state": "Kisumu",
    "latitude": -0.0952,
    "longitude": 34.7523,
    "market_type": "wholesale",
    "commodities_traded": [
      "MZE-DRY",
      "BEN-YGN",
      "GRG-KEN"
    ],
    "avg_daily_arrivals_tonnes": 340.0,
    "enam_integrated": false,
    "reporting_quality": "good"
  },
  {
    "mandi_id": "MKT-NWK",
    "name": "Nairobi Wakulima",
    "district": "Nairobi",
    "state": "Nairobi",
    "latitude": -1.2921,
    "longitude": 36.827,
    "market_type": "terminal",
    "commodities_traded": [
      "MZE-DRY",
      "BEN-YGN",
      "POT-RIR",
      "GRG-KEN"
    ],
    "avg_daily_arrivals_tonnes": 620.0,
    "enam_integrated": false,
    "reporting_quality": "good"
  },
  {
    "mandi_id": "MKT-KON",
    "name": "Kongowea",
    "district": "Mombasa",
    "state": "Mombasa",
    "latitude": -4.0277,
    "longitude": 39.6876,
    "market_type": "terminal",
    "commodities_traded": [
      "MZE-DRY",
      "BEN-YGN",
      "POT-RIR",
      "GRG-KEN"
    ],
    "avg_daily_arrivals_tonnes": 480.0,
    "enam_integrated": false,
    "reporting_quality": "good"
  },
  {
    "mandi_id": "MKT-ELD",
    "name": "Eldoret Main",
    "district": "Uasin Gishu",
    "state": "Uasin Gishu",
    "latitude": 0.5143,
    "longitude": 35.2698,
    "market_type": "wholesale",
    "commodities_traded": [
      "MZE-DRY",
      "BEN-YGN",
      "POT-RIR"
    ],
    "avg_daily_arrivals_tonnes": 410.0,
    "enam_integrated": false,
    "reporting_quality": "good"
  },
  {
    "mandi_id": "MKT-NAK",
    "name": "Nakuru Wakulima",
    "district": "Nakuru",
    "state": "Nakuru",
    "latitude": -0.3031,
    "longitude": 36.08,
    "market_type": "wholesale",
    "commodities_traded": [
      "MZE-DRY",
      "BEN-YGN",
      "POT-RIR"
    ],
    "avg_daily_arrivals_tonnes": 295.0,
    "enam_integrated": false,
    "reporting_quality": "good"
  },
  {
    "mandi_id": "MKT-KGM",
    "name": "Kangemi Market",
    "district": "Nairobi",
    "state": "Nairobi",
    "latitude": -1.268,
    "longitude": 36.7462,
    "market_type": "wholesale",
    "commodities_traded": [
      "MZE-DRY",
      "BEN-YGN",
      "POT-RIR"
    ],
    "avg_daily_arrivals_tonnes": 175.0,
    "enam_integrated": false,
    "reporting_quality": "moderate"
  },
  {
    "mandi_id": "MKT-KRT",
    "name": "Karatina",
    "district": "Nyeri",
    "state": "Nyeri",
    "latitude": -0.4833,
    "longitude": 37.1333,
    "market_type": "wholesale",
    "commodities_traded": [
      "MZE-DRY",
      "BEN-YGN",
      "POT-RIR"
    ],
    "avg_daily_arrivals_tonnes": 230.0,
    "enam_integrated": false,
    "reporting_quality": "good"
  },
  {
    "mandi_id": "MKT-KTZ",
    "name": "Kathonzweni",
    "district": "Makueni",
    "state": "Makueni",
    "latitude": -1.95,
    "longitude": 37.65,
    "market_type": "regulated",
    "commodities_traded": [
      "MZE-DRY",
      "BEN-YGN",
      "GRG-KEN"
    ],
    "avg_daily_arrivals_tonnes": 85.0,
    "enam_integrated": false,
    "reporting_quality": "moderate"
  },
  {
    "mandi_id": "MKT-MAC",
    "name": "Machakos Main Market",
    "district": "Machakos",
    "state": "Machakos",
    "latitude": -1.5167,
    "longitude": 37.2634,
    "market_type": "wholesale",
    "commodities_traded": [
      "MZE-DRY",
      "BEN-YGN",
      "GRG-KEN"
    ],
    "avg_daily_arrivals_tonnes": 110.0,
    "enam_integrated": false,
    "reporting_quality": "good"
  },
  {
    "mandi_id": "MKT-MRU",
    "name": "Nkubu",
    "district": "Meru",
    "state": "Meru",
    "latitude": 0.0571,
    "longitude": 37.6714,
    "market_type": "wholesale",
    "commodities_traded": [
      "MZE-DRY",
      "BEN-YGN",
      "POT-RIR"
    ],
    "avg_daily_arrivals_tonnes": 90.0,
    "enam_integrated": false,
    "reporting_quality": "good"
  },
  {
    "mandi_id": "MKT-KCH",
    "name": "Sondu- Kericho",
    "district": "Kericho",
    "state": "Kericho",
    "latitude": -0.3689,
    "longitude": 35.2833,
    "market_type": "wholesale",
    "commodities_traded": [
      "MZE-DRY",
      "BEN-YGN",
      "POT-RIR"
    ],
    "avg_daily_arrivals_tonnes": 75.0,
    "enam_integrated": false,
    "reporting_quality": "moderate"
  }
]
